xiaomi_ndef/__init__.py
xiaomi_ndef/_utils.py
xiaomi_ndef/base.py
xiaomi_ndef/handoff.py
xiaomi_ndef/mi_connect.py
xiaomi_ndef/ndef.py
xiaomi_ndef/nfc.py
xiaomi_ndef/tag.py
xiaomi_ndef/tnf.py
xiaomi_ndef/xiaomi.py
xiaomi_ndef/proto/MiConnectProtocol_pb2.py
xiaomi_ndef/proto/MiConnectProtocol_pb2.pyi
xiaomi_ndef/proto/__init__.py
xiaomi_ndef-0.1.2.dist-info/METADATA
xiaomi_ndef-0.1.2.dist-info/WHEEL
xiaomi_ndef-0.1.2.dist-info/licenses/LICENSE
xiaomi_ndef-0.1.2.dist-info/RECORD
