Metadata-Version: 2.1
Name: xiaomi-ndef
Version: 0.1.2
Summary: Encode and decode NDEF message using Xiaomi NFC protocol.
Project-URL: Homepage, https://github.com/XFY9326/XiaomiNDEF
Project-URL: Repository, https://github.com/XFY9326/XiaomiNDEF.git
Project-URL: Bug Tracker, https://github.com/XFY9326/XiaomiNDEF/issues
Author: XFY9326
Maintainer: XFY9326
License-Expression: MIT
License-File: LICENSE
Keywords: mi,ndef,ndef-library,nfc,xiaomi
Classifier: Development Status :: 4 - Beta
Classifier: Intended Audience :: Developers
Classifier: License :: OSI Approved :: MIT License
Classifier: Programming Language :: Python
Classifier: Programming Language :: Python :: 3
Classifier: Programming Language :: Python :: 3.10
Requires-Python: >=3.10
Requires-Dist: protobuf>=4.25.3
Requires-Dist: pyndef>=1.0.2
